mafic/__init__.py
mafic/__libraries.py
mafic/__main__.py
mafic/errors.py
mafic/events.py
mafic/filter.py
mafic/ip.py
mafic/node.py
mafic/player.py
mafic/playlist.py
mafic/plugin.py
mafic/pool.py
mafic/py.typed
mafic/region.py
mafic/search_type.py
mafic/stats.py
mafic/strategy.py
mafic/track.py
mafic/type_variables.py
mafic/typings/__init__.py
mafic/typings/common.py
mafic/typings/http.py
mafic/typings/incoming.py
mafic/typings/misc.py
mafic/typings/outgoing.py
mafic/utils/__init__.py
mafic/utils/classproperty.py
mafic/warnings.py
mafic-2.10.1.dist-info/LICENSE
mafic-2.10.1.dist-info/METADATA
mafic-2.10.1.dist-info/WHEEL
mafic-2.10.1.dist-info/RECORD
