Metadata-Version: 2.3
Name: mafic
Version: 2.10.1
Summary: A properly typehinted lavalink client for discord.py, nextcord, disnake and py-cord.
License: MIT
Keywords: nextcord,disnake,discord,disnake.py,lavalink,lavalink.py,pycord,py-cord
Author: ooliver1
Author-email: oliverwilkes2006@icloud.com
Requires-Python: >=3.8,<4.0
Classifier: Development Status :: 5 - Production/Stable
Classifier: Framework :: AsyncIO
Classifier: Framework :: aiohttp
Classifier: Intended Audience :: Developers
Classifier: License :: OSI Approved :: MIT License
Classifier: Operating System :: OS Independent
Classifier: Programming Language :: Python :: 3
Classifier: Programming Language :: Python :: 3.8
Classifier: Programming Language :: Python :: 3.9
Classifier: Programming Language :: Python :: 3.10
Classifier: Programming Language :: Python :: 3.11
Classifier: Programming Language :: Python :: 3.12
Classifier: Programming Language :: Python :: 3.13
Classifier: Topic :: Software Development :: Libraries
Classifier: Topic :: Software Development :: Libraries :: Python Modules
Classifier: Typing :: Typed
Provides-Extra: speedups
Requires-Dist: aiohttp (>=3.6.0,<4.0.0)
Requires-Dist: orjson (>=3.8.0,<4.0.0) ; extra == "speedups"
Requires-Dist: yarl (>=1.0.0,<2.0.0)
Project-URL: Homepage, https://github.com/ooliver1/mafic
Project-URL: Repository, https://github.com/ooliver1/mafic
